akeyless_auth_api/__init__.py
akeyless_auth_api/api_client.py
akeyless_auth_api/configuration.py
akeyless_auth_api/rest.py
akeyless_auth_api/api/__init__.py
akeyless_auth_api/api/default_api.py
akeyless_auth_api/models/__init__.py
akeyless_auth_api/models/access_params.py
akeyless_auth_api/models/access_rules.py
akeyless_auth_api/models/access_rules_type.py
akeyless_auth_api/models/access_type.py
akeyless_auth_api/models/account_reply_obj.py
akeyless_auth_api/models/account_status.py
akeyless_auth_api/models/algorithm.py
akeyless_auth_api/models/api_key_access_rules.py
akeyless_auth_api/models/auth_method_access_info.py
akeyless_auth_api/models/auth_method_role_association.py
akeyless_auth_api/models/auth_status_reply_obj.py
akeyless_auth_api/models/azure_ad_access_rules.py
akeyless_auth_api/models/create_access_reply_obj.py
akeyless_auth_api/models/create_account_creds_params.py
akeyless_auth_api/models/create_auth_method_reply_obj.py
akeyless_auth_api/models/create_role_auth_method_assoc_reply_obj.py
akeyless_auth_api/models/credentials_reply_obj.py
akeyless_auth_api/models/derivation_creds_reply_obj.py
akeyless_auth_api/models/derived_fragment_reply_obj.py
akeyless_auth_api/models/dynamic_secret_message_queue_info.py
akeyless_auth_api/models/dynamic_secret_mq_access_reply_obj.py
akeyless_auth_api/models/dynamic_secret_producer_creds_reply_obj.py
akeyless_auth_api/models/error_reply_obj.py
akeyless_auth_api/models/fragment_type.py
akeyless_auth_api/models/fragments_derivations_creds.py
akeyless_auth_api/models/get_access_reply_obj.py
akeyless_auth_api/models/get_accesses_reply_obj.py
akeyless_auth_api/models/get_account_auth_methods_reply_obj.py
akeyless_auth_api/models/get_account_details_reply_obj.py
akeyless_auth_api/models/get_account_roles_reply_obj.py
akeyless_auth_api/models/get_auth_method_reply_obj.py
akeyless_auth_api/models/get_fragment_details_reply_obj.py
akeyless_auth_api/models/get_item_reply_obj.py
akeyless_auth_api/models/get_role_reply_obj.py
akeyless_auth_api-0.1.1.dist-info/METADATA
akeyless_auth_api-0.1.1.dist-info/WHEEL
akeyless_auth_api-0.1.1.dist-info/top_level.txt
akeyless_auth_api-0.1.1.dist-info/RECORD
